{
  "helmet_type": {
    "precision": 1.0,
    "recall": 1.0,
    "f1-score": 1.0,
    "support": 16,
    "confused_with": {}
  },
  "product_type": {
    "precision": 1.0,
    "recall": 1.0,
    "f1-score": 1.0,
    "support": 8,
    "confused_with": {}
  },
  "gender": {
    "precision": 1.0,
    "recall": 1.0,
    "f1-score": 1.0,
    "support": 13,
    "confused_with": {}
  },
  "product_name": {
    "precision": 1.0,
    "recall": 1.0,
    "f1-score": 1.0,
    "support": 822,
    "confused_with": {}
  },
  "bugi_type": {
    "precision": 1.0,
    "recall": 1.0,
    "f1-score": 1.0,
    "support": 17,
    "confused_with": {}
  },
  "province": {
    "precision": 1.0,
    "recall": 1.0,
    "f1-score": 1.0,
    "support": 129,
    "confused_with": {}
  },
  "vehicle_type": {
    "precision": 0.925,
    "recall": 1.0,
    "f1-score": 0.961038961038961,
    "support": 74,
    "confused_with": {}
  },
  "filter_type": {
    "precision": 1.0,
    "recall": 1.0,
    "f1-score": 1.0,
    "support": 70,
    "confused_with": {}
  },
  "model_type": {
    "precision": 1.0,
    "recall": 1.0,
    "f1-score": 1.0,
    "support": 60,
    "confused_with": {}
  },
  "micro avg": {
    "precision": 0.9950617283950617,
    "recall": 1.0,
    "f1-score": 0.9975247524752474,
    "support": 1209
  },
  "macro avg": {
    "precision": 0.9916666666666667,
    "recall": 1.0,
    "f1-score": 0.9956709956709956,
    "support": 1209
  },
  "weighted avg": {
    "precision": 0.9954094292803971,
    "recall": 1.0,
    "f1-score": 0.9976152879378686,
    "support": 1209
  },
  "accuracy": 0.9985294117647059
}